sqlyte.py
sqlyte-0.1.2.dist-info/METADATA
sqlyte-0.1.2.dist-info/WHEEL
sqlyte-0.1.2.dist-info/RECORD
