Metadata-Version: 2.1
Name: sqlyte
Version: 0.1.2
Summary: a simple SQLite interface
License: BSD-2-Clause
Keywords: SQLite
Author: Angelo Gladding
Author-email: angelo@ragt.ag
Requires-Python: >=3.10,<3.11
Classifier: License :: OSI Approved :: BSD License
Classifier: Programming Language :: Python :: 3
Classifier: Programming Language :: Python :: 3.10
Requires-Dist: pendulum (>=2.1.2,<3.0.0)
